amqpeek/__init__.py
amqpeek/base_config.py
amqpeek/cli.py
amqpeek/exceptions.py
amqpeek/monitor.py
amqpeek/notifier.py
amqpeek/py.typed
amqpeek-0.0.7.dist-info/entry_points.txt
amqpeek-0.0.7.dist-info/LICENSE
amqpeek-0.0.7.dist-info/WHEEL
amqpeek-0.0.7.dist-info/METADATA
amqpeek-0.0.7.dist-info/RECORD
