Metadata-Version: 2.1
Name: amqpeek
Version: 0.0.7
Summary: A flexible RMQ monitor that keeps track of RMQ, notifying you over multiple channels when connections cannot be made, queues have not been declared, and when queue lengths increase beyond specified limits.
Home-page: https://github.com/steveYeah/amqpeek
License: MIT
Author: steveYeah
Author-email: hutchinsteve@gmail.com
Requires-Python: >=3.8,<4.0
Classifier: License :: OSI Approved :: MIT License
Classifier: Programming Language :: Python :: 3
Classifier: Programming Language :: Python :: 3.8
Requires-Dist: PyYAML (>=5.3.1,<6.0.0)
Requires-Dist: click (>=7.1.2,<8.0.0)
Requires-Dist: pika (>=1.1.0,<2.0.0)
Requires-Dist: slacker (>=0.14.0,<0.15.0)
Project-URL: Repository, https://github.com/steveYeah/amqpeek
